MANIFEST.in
README.md
requirements.txt
setup.py
safeworder/Replacer.py
safeworder/__init__.py
safeworder.egg-info/PKG-INFO
safeworder.egg-info/SOURCES.txt
safeworder.egg-info/dependency_links.txt
safeworder.egg-info/not-zip-safe
safeworder.egg-info/requires.txt
safeworder.egg-info/top_level.txt
safeworder/mappings/mapping_obscenity.xlsx
safeworder/mappings/mapping_toxicity.xlsx
safeworder/mappings/test.json
tests/obscenity.json