Metadata-Version: 1.0
Name: safeworder
Version: 1.0.2
Summary: Replace dirty strings with clean ones
Home-page: https://github.com/Tommel71/safeworder
Author: Tommel
Author-email: UNKNOWN
License: MIT
Platform: UNKNOWN
